{
  "card_id": 1242,
  "card_url": "https://www.card-gorilla.com/card/detail/1242",
  "card_name": "스피킹맥스 하나카드",
  "issuer": "하나카드",
  "inactive": false,
  "brands": [
    "Mastercard"
  ],
  "annual_fee": {
    "domestic": "국내전용 20,000원",
    "international": "해외겸용 20,000원"
  },
  "required_spending": null,
  "required_spending_amount": null,
  "benefits": [
    {
      "type": "교육/육아",
      "summary": "스피킹맥스/뇌새김 장기할부 서비스",
      "details": [
        "스피킹맥스/뇌새김 장기할부 서비스",
        "10만원 이상 이용 시",
        "할부개월수 12개월, 2개월 시 원금균등 상환방식 적용",
        "스피킹맥스/뇌새김 제품 또는 서비스 결제 시, 결제 금액을 12/24개월 할부로 이용하고, 이후 할부수수료가 포함된 금액을 원금균등방식으로 상환하는 서비스입니다.",
        "원금균등상환: 매월 동일한 원금이 상환되고, 이자는 잔액에 따라 계산되는 방식",
        "할부수수료는 개인별 일반 할부 수수료율이 적용됩니다.",
        "할부승인금액이 10만원 미만이거나 12개월, 24개월 할부가 아닐경우 장기할부 및 할인서비스가 적용되지 않습니다.",
        "할부이용 건은 이용 월의 사용금액으로 전액 합산처리 됩니다."
      ]
    },
    {
      "type": "교육/육아",
      "summary": "스피킹맥스/뇌새김 장기할부 청구 할인 서비스",
      "details": [
        "스피킹맥스/뇌새김 장기할부 청구 할인 서비스",
        "서비스 제공조건",
        "지난달 이용실적 산정 제외 대상: 국세, 지방세, 공과금(인터넷/모바일앱을 통한 공과금 납부금액 포함), 국민연금/고용보험료/산재보험료/건강보험료료 납부금액, 상품권 및 기프트카드 구매, 선불카드 및 선불 전자 지급수단(하나머니 등) 충전금액, 도시가스/수도/전기요금, 아파트관리비, 대학등록금, 초·중·고 학교 납입금",
        "지난달 1일부터 말일까지(승인시점 기준) 국내외 일시불/할부 이용금액 40만원/ 80만원/120만원 이상시 서비스가 제공됩니다.",
        "할부이용 건은 이용 월의 사용금액으로 전액 합산처리 됩니다.",
        "교통요금, 통신요금, 해외 이용금액 등 무승인 매입(카드사의 승인없이 이용금액이 카드사로 접수됨)의 경우 매출 접수 월의 이용금액으로 반영됩니다.",
        "최초카드 사용등록 후 다음달 말일까지 지난달 40만원이상~80만원 미만 기준으로 서비스가 제공됩니다.",
        "매출 취소 시, 취소 접수된 월의 이용금액에서 차감됩니다."
      ]
    },
    {
      "type": "적립",
      "summary": "국내 가맹점 0.7% 청구할인 ※스피킹맥스/뇌새김 장기할부 미이용 또는 종료시",
      "details": [
        "생활할인 서비스(스피킹맥스/뇌새김 장기할부 미이용 또는 종료 시)\n국내가맹점 0.7% 청구할인",
        "전월실적 조건없음 / 할인한도 및 횟수 제한 없음",
        "서비스 제공조건",
        "지난달 이용실적 조건 없습니다.",
        "대상 가맹점은 하나카드에 등록된 가맹점 기준에 따릅니다.",
        "할부이용 건은 이용 월의 사용금액으로 전액 합산처리 됩니다.",
        "교통요금, 통신요금, 해외 이용금액 등 무승인 매입(카드사의 승인없이 이용금액이 카드사로 접수됨)의 경우 매출 접수 월의 이용금액으로 반영됩니다.",
        "매출 취소 시, 취소 접수된 월의 이용금액에서 차감됩니다.",
        "할인 제외 대상: 국세, 지방세, 공과금(인터넷/모바일앱을 통한 공과금 납부금액 포함),국민연금/고용보험료/산재보험료/건강보험료 납부금액, 상품권 및 기프트카드 구매, 선불카드 및 선불전자 지급수단(하나머니 등) 충전금액, 도시가스/수도/전기요금, 아파트관리비, 대학등록금, 초·중·고 학교 납입금, 무이자 할부 이용 금액 전체"
      ]
    }
  ],
  "caution": []
}