{
  "card_id": 990,
  "card_url": "https://www.card-gorilla.com/card/detail/990",
  "card_name": "신협-현대카드 MY BUSINESS M Edition2",
  "issuer": "현대카드",
  "inactive": false,
  "brands": [
    "Mastercard"
  ],
  "annual_fee": {
    "domestic": "국내전용 35,000원",
    "international": "해외겸용 40,000원"
  },
  "required_spending": null,
  "required_spending_amount": null,
  "benefits": [
    {
      "type": "비즈니스",
      "summary": "MY BUSINESS 사업지원서비스",
      "details": [
        "AI 세금신고",
        "부가세, 종합소득세 등 세금신고 자동화서비스 제공",
        "국세청에 등록된 사업용 신용카드 데이터를 수집하여 누락 없는 세금신고 가능",
        "AI 세금신고 자동화서비스 이용요금 건당 3만3천원(그 외 부가서비스는 무료)",
        "부가세신고 지원",
        "매입세액공제 대상 분류",
        "* 현대카드 MY BUSINESS 이용내역 중 매입세액공제 대상 분류",
        "매출·매입내역 증빙",
        "* 전자세금계산서, 현금영수증, MY BUSINESS 카드 이용내역을 수집하여 매출·매입내역 합계표 제공",
        "전자세금계산서",
        "비즈플레이에서 제공하는 전자세금계산서 월 250건까지 무료,",
        "* 이후 초과 발급 시 건당 200원 이용요금 부과",
        "간편장부",
        "매출·매입내역 수집 후 간편장부 기능 제공",
        "세무상담",
        "전문 세무사와 온라인 무료 상담",
        "사업장 매출분석",
        "현대카드 회원의 이용내역을 기준으로 MY BUSINESS 회원의 가맹점 매출 현황 및 방문 고객 분석자료 제공",
        "상권분석",
        "K텔레콤 지오비전 심층상권분석 보고서를 현대카드 MY BUSINESS로 결제 시 최초 1회에 한하여 무료, 이후 건당 3만원 이용요금 부과",
        "사업 관련 지식·정보",
        "분야별 전문가들의 사업 노하우 제공",
        "해외 소상공인 사업정보 제공",
        "사업 아이템별 현황 및 특성 분석자료 제공",
        "장기카드대출(카드론)",
        "현대카드 MY BUSINESS 회원이 장기카드대출(카드론) 이용 시 초기 1회 차 9.5% 우대 이자율 적용",
        "3개월 단위로 카드 이용 실적 및 가맹점 매출에 따라 4%p까지 할인 이자율 적용",
        "장기카드대출(카드론) 대출 이자율 5.5~23.5%",
        "MY BUSINESS 카드 이용내역 중 온라인 PG결제 대행내역 및 가맹점 정보 확인 불가내역은 매입세액 공제대상 분류 제외",
        "매출·매입내역 증빙을 위한 정보 수집은 회원 본인이 비즈플레이에서 직접 설정 후 이용 가능하며 국세청 및 여신금융협회에서 확인 가능한 대상에 한함",
        "사업장 매출분석은 현대카드 가맹점주 사업자에 한하여 이용 가능",
        "장기카드대출(카드론) 할인 이자율 적용 기준",
        "장기카드대출(카드론) 이용 조건 및 혜택은 이용 실적, 신용 상태에 따라 차등 적용",
        "* 카드 이용 실적 : 카드 이용 한도 사용률 50% 이상 시 1%p, 70% 이상 시 2%p 적용",
        "* 가맹점 매출 : 현대카드 가맹점 중 3개월간 월평균 매출액 2천만원 이상 시 1%p, 5천만원 이상 시 2%p 적용",
        "부가세신고 지원, 전자세금계산서, 간편장부, 세무상담은 비즈플레이에서 제공하며 상권분석서비스는 SK텔레콤에서 제공",
        "사업장 홍보 문자메시지 서비스는 2016년 9월 30일까지 제공되며 이후 이용 불가",
        "자세한 내용 및 서비스 이용 방법은 현대카드 MY BUSINESS 홈페이지(mybusiness.hyundaicard.com) > 사업지원서비스 참고",
        "사업지원서비스 관련 문의 : 현대카드 MY BUSINESS 고객센터(1588-0101)",
        "AI 세금신고 관련 문의 : 널리소프트 고객센터(02-1588-5368)",
        "부가세신고 지원 관련 문의 : 비즈플레이 고객센터(1670-9737)"
      ]
    },
    {
      "type": "금융",
      "summary": "현금카드 서비스",
      "details": [
        "거래 신협 방문 후 현금카드 기능 탑재 가능"
      ]
    },
    {
      "type": "적립",
      "summary": "업종별 0.5~2% 적립 월 100만원 이상 이용 시 1.5배 적립",
      "details": [
        "업종별 0.5~2% 적립\n월 100만원 이상 이용 시 1.5배 적립(0.75~3%)",
        "당월 이용금액 50만원 이상 이용 시 M포인트 적립",
        "신규 발급 시 발급일 포함 2회차 결제일자에 포함되는 이용 건까지 50만원 미만 이용 시에도 업종별 적립률 제공",
        "M포인트 적립 실적기준은 당월 결제일자에 청구된 본인 + 가족카드의 일시불 및 할부금액 기준",
        "업종별 적립률",
        "특별적립률",
        "현대 기아차 신차 구매 시 1.5% 적립",
        "GS칼텍스 주유 시 리터당 60 M포인트 적립",
        "하이패스 이용금액 2% 적립",
        "맥스무비 온라인 예매 이용금액 4% 적립 (M포인트 사용 시 적립제외 / 18.11.16~19.11.15)",
        "추가 M포인트",
        "현대카드 홈페이지를 통해 제휴 온라인쇼핑몰에 접속하여 결제 시 M포인트 추가 적립",
        "조건 없이 누구나 가입하고, 자동으로 통장포인트 월 2% 적립 받아 신차 구매 시 사용",
        "M포인트 적립 및 관리 기준",
        "실적 기준",
        "당월 이용금액은 결제일자에 청구된 신협-현대카드 MY BUSINESS M Edition2 본인 + 가족카드의 일시불 및 할부금액",
        "예시 : 결제일이 25일인 경우, 전월 14일 ~ 당월 13일에 이용한 금액을 청구",
        "할부, 일부결제금액이월약정(리볼빙) 이용 시 최초 결제일자에 실적포함",
        "결제일자 변경, 전표매입 지연, 매출취소, 세이브-오토 등의 경우 실적합산 기간 및 금액이 달라질 수 있음",
        "신협-현대카드 MY BUSINESS M Edition2 이용실적만 인정되며, 그 외 M계열카드의 실적은 합산 제외 (M계열카드 실적이 합산되는 것이 아닌, 해당 카드상품의 이용실적만 합산)",
        "적립 대상",
        "국내 및 해외에서 사용한 모든 카드 이용대금의 입금액",
        "1회 이용금액 천원 미만 단위는 제하고 적립",
        "입금액 기준으로 적립 (부분 입금 및 연체금액 입금 시에도 포인트 적립)",
        "부분 입금 및 결제일 이후 연체금액 입금 시 M포인트 적립 (2010년 7월 1일 결제일부터 시행)",
        "부분 입금 시에는 단일 결제건 별로 완납 처리되어야 해당 건 포인트 적립",
        "부분 입금 시 현행 입금공제 순서에 따라 입금 인정되며, 입금 인정된 금액에 한하여 M포인트 적립",
        "입금공제순서(우선순위 순)",
        "① 전월 미납금 > 당월 납부금",
        "② 지연 배상금 > 수수료 > 할부 > 일시불 > 단기카드대출(현금서비스)",
        "③ 최초 이용액부터 순차적으로 입금액 인정",
        "연체대금 입금액에 대한 M포인트는 입금 완료된 날로부터 10일 이후 확인 가능",
        "적립 제외",
        "장기카드대출(카드론), 단기카드대출(현금서비스), 연회비, 제수수료, 이자, 지방세ㆍ국세 등 세금 납부 건",
        "도시가스요금, 초·중·고교 학교납입금, 대학·대학원 등록금 납부 결제 건, 자동납부서비스 이용수수료",
        "당사 모든 할인서비스 및 무이자할부 이용금액",
        "적립 시기",
        "결제일 또는 이용대금 입금 완료된 날로부터 2~10일 이내 적립",
        "부분 입금 및 연체금액 입금 포함",
        "포인트 조정 및 참여 시간의 전송 누락 등에 따라 최장 40일 정도 소요될 수 있음",
        "선입금하는 경우, 원 결제일로 부터 2~10일 이내 적립",
        "세이브-오토(선지급 포인트 서비스) 이용 회원의 경우 적립 시기 상이",
        "소지자",
        "카드 소지 회원의 주민등록번호 기준으로 적립",
        "M포인트 적립카드 2종 이상 소유 시, 각 카드별 M포인트 적립금액은 소지자의 주민등록번호 1개로 합산하여 적립",
        "가족카드 이용 시 본인과 가족 각각의 주민등록번호로 별도 적립",
        "가족카드 이용 시 본인 회원과 가족카드 회원의 M포인트를 상호 양도하여 사용 가능",
        "양도 방법 : 고객센터 1577-6000, 현대카드 홈페이지에 로그인하여 M포인트 양도 신청",
        "적립 한도",
        "1회 및 연간 적립한도 제한 없음.",
        "이용금액에 따라 한도 제한 없이 적립(일부 특별 적립처는 별도 기준 적용)",
        "유효기간",
        "최초 포인트 적립 월로부터 60개월(5년)간 유효하며, 미사용한 포인트는 적립 60개월 경과 후 선입선출에 의거 월 단위로 자동 소멸",
        "M포인트 유효기간은 청구서 내 명시",
        "유효기간 만료 및 만료 예정 포인트는 현대카드 홈페이지에서 조회 가능",
        "M포인트 유효기간 만료에 따른 만료 적용은 해당 월 첫 번째 일요일에 일괄 처리(만료일 전일 토요일까지 포인트 사용 가능)",
        "M포인트 사용 시 먼저 적립된 M포인트의 순서대로 소진",
        "정지(연체 등)/해지/탈회 회원",
        "정지(연체 등)/해지/탈회 등 카드 이용계약 종료 시 회원의 잔여 M포인트는 기존에 부여된 유효기간까지 유지되며,",
        "예외적으로 유효한 카드가 없는 경우에도 카드사가 정한 일부 사용처에서 사용 가능",
        "카드 해지 시 잔여 M포인트는 H-Coin으로 전환하여 회원의 선택에 따라 미상환 카드대금을 결제하거나,",
        "회원의 카드대금 출금계좌로 입금 가능",
        "잔여 M포인트 유효기간 내 회원이 재가입하여 카드 사용이 정상일 때, 해당 잔여 M포인트도 사용 가능",
        "기타 포인트 소멸과 관련된 내용은 현대카드 개인회원 약관 제15조 제1항에 따름",
        "상기 업종별 적립 포인트는 대표 가맹점 업종에 따른 예시이므로 실제 적립내역과 다를 수 있습니다.",
        "당사 모든 할인서비스 및 무이자할부ㆍ부분 무이자할부 이용금액은 M포인트 적립 제외되며 상세 내용은 'M포인트 적립 및 관리 기준 안내'를 참고하세요.",
        "공동가맹점이란?",
        "* 가맹점 사정에 따라 일부 가맹점의 경우 현대카드와 가맹점 계약 체결이 없을 수도 있습니다.",
        "* 이 경우에도 [가맹점 공동 이용제도]에 따라 회원에 대한 거래 승인을 일반 가맹점과 동일한 방법으로 신용카드 조회기를 이용하여 거래 승인을 받을 수 있습니다.",
        "* 공동가맹점 이용제도 : 여러 신용카드 가맹점에 가입하지 않고 1개 이상의 카드사에만 가맹점으로 가입하면 국내에서 발행된 모든 신용카드에 대하여 신용판매할 수 있는 제도",
        "약관 제15조 제3항에 따라 회원에게 제공되는 M포인트 적립/사용서비스는 당사의 영업정책이나 제휴사의 사정에 따라 변경 또는 중단될 수 있으며 그 내용은 사전에 공지하여 드립니다."
      ]
    }
  ],
  "caution": [
    "유의사항",
    "유의사항"
  ]
}