{
  "card_id": 213,
  "card_url": "https://www.card-gorilla.com/card/detail/213",
  "card_name": "I’m WONDERFUL",
  "issuer": "롯데카드",
  "inactive": "신규발급이 중단된 카드입니다.",
  "brands": [
    "VISA",
    "Mastercard"
  ],
  "annual_fee": {
    "domestic": "국내전용 10,000원",
    "international": "해외겸용 10,000원"
  },
  "required_spending": null,
  "required_spending_amount": null,
  "benefits": [
    {
      "type": "모든가맹점",
      "summary": "기본할인 - 국내외 가맹점 0.7 % 결제일 할인",
      "details": [
        "국내외 가맹점 0.7 % 결제일 할인",
        "지난달 실적조건 없이, 할인한도 없이 적용됩니다.",
        "롯데카드 I’m WONDERFUL 할인 혜택 공통 안내",
        "기본 할인과 특별 할인은 중복 적용되지 않으며, 할인금액이 더 큰 혜택으로 적용됩니다.",
        "모든 할인 혜택은 롯데카드에 등록된 업종을 기준으로 적용됩니다.",
        "할부 이용 시 이용일을 기준으로 전체 금액에 대하여 할인 혜택이 제공됩니다.",
        "할인 적용 제외 대상 : 모든 가맹점 무이자할부·슬림할부 이용금액, 단기카드대출(현금서비스), 장기카드대출(카드론), 국세, 지방세, 공과금, 건강보험, 국민연금, 고용보험, 산재보험, 장애인 고용부담금, 아파트관리비, 대학등록금, 오토 · 스마트 캐시백 신청 이용금액, 기프트 · 선불카드 충전, 상품권(모바일상품권 포함)구매, 연회비, 이자 및 각종 수수료",
        "결제일 할인 이용기준",
        "롯데카드의 다른 결제일 할인 혜택과 중복 시 할인금액이 더 큰 혜택으로 적용됩니다.",
        "할인이 적용된 결제 건을 취소하는 경우 롯데카드에 접수되고 약 2~3일 후에 할인한도가 복원됩니다. 복원 전 결제건은 승인 시점 기준 할인 한도로 적용되며, 한도 복원 후에 별도 소급적용되지 않습니다.",
        "결제 취소 건 접수 여부는 롯데카드 홈페이지(www.lottecard.co.kr)에서 회원가입 후, 마이페이지 > 이용내역조회 > 카드이용취소내역에서 확인할 수 있습니다."
      ]
    },
    {
      "type": "할인",
      "summary": "특별할인 - 건별 10만원 이상 결제 시 1.4% 결제일 할인",
      "details": [
        "건별 10만원 이상 결제 시 1.4% 결제일 할인",
        "지난달 실적조건 없이 적용되며, 월 할인한도는 10만원입니다.",
        "월 할인한도 초과 시 기본할인이 적용됩니다.",
        "롯데카드 I’m WONDERFUL 할인 혜택 공통 안내",
        "기본 할인과 특별 할인은 중복 적용되지 않으며, 할인금액이 더 큰 혜택으로 적용됩니다.",
        "모든 할인 혜택은 롯데카드에 등록된 업종을 기준으로 적용됩니다.",
        "할부 이용 시 이용일을 기준으로 전체 금액에 대하여 할인 혜택이 제공됩니다.",
        "할인 적용 제외 대상 : 모든 가맹점 무이자할부·슬림할부 이용금액, 단기카드대출(현금서비스), 장기카드대출(카드론), 국세, 지방세, 공과금, 건강보험, 국민연금, 고용보험, 산재보험, 장애인 고용부담금, 아파트관리비, 대학등록금, 오토 · 스마트 캐시백 신청 이용금액, 기프트 · 선불카드 충전, 상품권(모바일상품권 포함)구매, 연회비, 이자 및 각종 수수료",
        "결제일 할인 이용기준",
        "롯데카드의 다른 결제일 할인 혜택과 중복 시 할인금액이 더 큰 혜택으로 적용됩니다.",
        "할인이 적용된 결제 건을 취소하는 경우 롯데카드에 접수되고 약 2~3일 후에 할인한도가 복원됩니다. 복원 전 결제건은 승인 시점 기준 할인 한도로 적용되며, 한도 복원 후에 별도 소급적용되지 않습니다.",
        "결제 취소 건 접수 여부는 롯데카드 홈페이지(www.lottecard.co.kr)에서 회원가입 후, 마이페이지 > 이용내역조회 > 카드이용취소내역에서 확인할 수 있습니다."
      ]
    }
  ],
  "caution": [
    "L.POINT",
    "롯데멤버스(주) 고객정보 제공에 동의하신 회원만 L.POINT 회원가입이 가능합니다.",
    "L.POINT는 L.POINT 제휴사 이용 시 결제금액에 따라 적립받고 현금처럼 사용가능한 포인트 입니다.",
    "해당 카드로 결제 시 롯데카드가 제공하는 L.POINT 적립서비스가 제공되지 않습니다.",
    "다른 L.POINT 제휴사가 제공하는 L.POINT는 적립 가능합니다.",
    "L.POINT의 사용과 적립에 관한 자세한 내용은 L.POINT 홈페이지(www.lpoint.com)에서 확인할 수 있습니다."
  ]
}