{
  "card_id": 1167,
  "card_url": "https://www.card-gorilla.com/card/detail/1167",
  "card_name": "엠비에이(MBA) 카드",
  "issuer": "롯데카드",
  "inactive": "신규발급이 중단된 카드입니다.",
  "brands": [
    "VISA"
  ],
  "annual_fee": {
    "domestic": "국내전용 195,000원",
    "international": "해외겸용 200,000원"
  },
  "required_spending": null,
  "required_spending_amount": null,
  "benefits": [
    {
      "type": "바우처",
      "summary": "매년 차량관련 바우처/골프 바우처/호텔 레스토랑 바우처/ 캠핑, 여행 상품 바우처 제공(택 1)",
      "details": [
        "매년 차량관련(주유권 및 엔진오일, 차량용품) 바우처/골프(부킹 시 그린피 지원) 바우처/호텔 레스토랑 바우처/ 캠핑, 여행 상품 바우처 제공(택 1)",
        "이용방법",
        "롯데카드 홈페이지 혜택> 나의 카드 혜택 또는 롯데카드 VIP 고객센터(1577-8100)를 통해 신청",
        "이용조건",
        "아래 이용조건을 충족하시는 회원님에게만 연1회 택1하여 제공됩니다.",
        "최초 발급월 기준 일시불 및 할부 이용실적 500만원 이상 (단기카드대출(현금서비스)및 장기카드대출(카드론)제외)",
        "연회비 납부회원 및 정상적으로 사용할 수 있는 카드 회원에게만 제공됩니다.(연회비 면제, 가족카드 제외)"
      ]
    },
    {
      "type": "주유소",
      "summary": "오일리지 적립",
      "details": [
        "적립 마일리지 : 오일리지(Oileage)",
        "적립",
        "전 주유소 리터당 80원 오일리지 적립",
        "일반가맹점 0.5% 오일리지 적립",
        "이용",
        "SK주유소, GS칼텍스 주유포인트로 교환(1:1) (단, 5만 오일리지 이상 적립 후, 1만 단위 교환)",
        "오일리지(Oileage)란?",
        "롯데카드가 자체 개발한 오토 상품 전용 주유 특화 마일리지로, SK주유소 및 GS칼텍스에서 현금처럼 사용하실 수 있는 주유포인트 교환 가능한 마일리지 입니다.",
        "교환방법",
        "VIP 고객센터(1577-8100) 통해 오일리지 교환 신청",
        "이용조건",
        "전 주유소 리터당 80원 오일리지 적립은 일 1회, 월 40만원까지 적립 가능합니다.",
        "무이자 할부 이용 및 아파트 관리비, 세금 등 일부 가맹점 이용 실적은 적립되지 않습니다.",
        "오일리지는 적립월부터 60개월(5년)간 유효하며, 그 이후 최초로 적립된 오일리지부터 월단위로 소멸됩니다.",
        "SK주유소, GS칼텍스 주유포인트는 롯데카드 전용 포인트로 주유소 멤버십 포인트와 합산되지 않습니다.",
        "매출 취소 시 취소 매출에 해당하는 오일리지는 차감됩니다. (단, 잔여 오일리지 부족 시에는 추후 적립 오일리지에서 해당 금액만큼 차감처리됩니다.)",
        "오일리지 교환비율은 6개월 전 사전고지 후 변동될 수 있습니다."
      ]
    },
    {
      "type": "프리미엄 서비스",
      "summary": "엠비에이(MBA) 카드 프리미엄 서비스",
      "details": [
        "Auto",
        "프리미엄 세차 서비스(월 1회, 연 6회)",
        "프리미엄 왁스코팅 서비스(월 1회, 연 2회)",
        "* 프리미엄 오토라운지(02-3140-1730)를 통해 사전 예약 후 이용 가능합니다.",
        "전국 주요도시 주차 무료(월 1회, 연 6회)",
        "프리미엄 엔진오일 무료 교환 서비스(연 1회)",
        "자동차보험 가입 시 5% 오일리지 적립 서비스(연 1회)",
        "이용조건",
        "프리미엄 세차, 프리미엄 왁스코팅, 전국 주요도시 주차 무료 서비스는 지난달(1일~말일)카드 이용금액이 70만원 이상(단기카드대출(현금서비스) 및 장기카드대출(카드론), 주유실적 제외, 매출접수분에 한함)인 회원에 한하여 제공됩니다.",
        "신규 회원님의 경우, 발급 후 2개월 동안(카드사용등록월 포함~2개월차 말일까지)은 카드 이용금액이 10만원 이상(단기카드대출(현금서비스)및 장기카드대출(카드론), 주유실적 제외, 매출접수분에 한함)인 회원에 한하여 제공됩니다.",
        "이 서비스의 이용기준은 매년 1월 1일~12월 31일로 산정되며, 카드회원 본인에 한하여 서비스를 이용 하실 수 있습니다.",
        "프리미엄 엔진오일 무료 교환 서비스는 최초 엠비에이(MBA)카드 발급월 기준 12개월동안 이용금액이 1천만원 이상(단기카드대출(현금서비스), 장기카드대출(카드론) 제외)인 회원에 한하여 제공됩니다.",
        "이 서비스는 회원 상태가 정상인 회원님에 한하여 제공되며, 서비스 이용 횟수 초과 시 서비스를 이용 하실 수 없습니다.",
        "자동차보험 가입 시 5% 오일리지 적립 서비스는 연 1회, 3만 마일리지까지 적립 가능합니다.",
        "Hotel",
        "국내 특급호텔 카페 라운지 커피 서비스(월 1회, 연 3회)",
        "Golf",
        "국내 실외 골프연습장 무료 서비스(월 1회, 연 6회)",
        "국내 프리미엄 골프장 부킹 서비스",
        "프리미엄 골프장 부킹 시 그린피 및 골프용품 할인 서비스",
        "이용조건",
        "이 서비스는 지난달(1일~말일)카드 이용금액이 70만원 이상(단기카드대출(현금서비스), 장기카드대출(카드론), 주유실적 제외,매출접수분에 한함))인 회원에 한하여 제공됩니다.",
        "신규 회원님의 경우, 발급 후 2개월 동안(카드사용등록월 포함~2개월차 말일까지)은 카드 이용금액이 10만원 이상 (단기카드대출(현금서비스), 장기카드대출(카드론), 주유실적 제외, 매출접수분에 한함)인 회원에 한하여 제공됩니다.",
        "이 서비스의 이용기준은 매년 1월 1일~12월 31일로 산정되며, 카드회원 본인에 한하여 서비스를 이용하실 수 있습니다.",
        "이 서비스는 회원 상태가 정상인 회원님에 한하여 제공되며, 서비스 이용 횟수 초과 시 서비스를 이용하실 수 없습니다.",
        "국내 프리미엄 골프장 부킹, 프리미엄 골프장 부킹 시 그린피 및 골프용품 할인 서비스는 롯데카드 홈페이지 (쇼핑·여행·라이프 > 골프) 를 통해 확인하시기 바랍니다.",
        "이 서비스는 다른 프로모션 및 혜택과 중복 사용 및 현금화될 수 없습니다.",
        "Concierge",
        "국내 공항라운지 무료 이용(연 3회)",
        "이경민포레 무료 뷰티서비스(월 1회, 연 6회)",
        "이용조건",
        "이 서비스는 지난달(1일~말일)카드 이용금액이 70만원 이상(단기카드대출(현금서비스), 장기카드대출(카드론), 주유실적 제외, 매출접수분에 한함))인 회원에 한하여 제공됩니다.",
        "신규 회원님의 경우, 발급 후 2개월 동안(카드사용등록월 포함~2개월차 말일까지)은 카드 이용금액이 10만원 이상 (단기카드대출(현금서비스), 장기카드대출(카드론), 주유실적 제외, 매출접수분에 한함)인 회원에 한하여 제공됩니다.",
        "이 서비스의 이용기준은 매년 1월 1일~12월 31일로 산정되며, 카드회원 본인에 한하여 서비스를 이용하실 수 있습니다.",
        "이 서비스는 회원 상태가 정상인 회원님에 한하여 제공되며, 서비스 이용 횟수 초과 시 서비스를 이용하실 수 없습니다.",
        "국내 공항라운지 무료 이용 서비스는 스카이허브 라운지, 마티나(인천공항 제 1여객터미널)라운지에서 본인 및 가족회원 합산하여 통합 연 3회 이용 하실 수 있습니다.",
        "이경민포레 무료 뷰티 서비스는 예약 초과 시 이용이 불가할 수 있으므로, 반드시 사전 예약하시기 바랍니다.",
        "이 서비스는 다른 프로모션 및 혜택과 중복 사용 및 현금화될 수 없습니다.",
        "Dining",
        "국내 공항 카페 및 국내 프리미엄 카페 무료 서비스(각 월 1회, 연 3회)",
        "국내 공항 카페 대상 가맹점",
        "프리미엄 카페 대상 가맹점",
        "국내 프리미엄 베이커리 3만원 이상 결제 시 1만 5천원 할인(월 1회, 연 3회)",
        "국내 프리미엄 레스토랑 6만원 이상 결제 시 3만원 할인(월 1회, 연 3회)",
        "이용조건",
        "이 서비스는 지난달(1일~말일)카드 이용금액이 70만원 이상(단기카드대출(현금서비스), 장기카드대출(카드론), 주유실적 제외, 매출접수분에 한함)인 회원에 한하여 제공됩니다.",
        "신규 회원님의 경우, 발급 후 2개월 동안(카드사용등록월 포함~2개월차 말일까지)은 카드 이용금액이 10만원 이상 (단기카드대출(현금서비스), 장기카드대출(카드론), 주유실적 제외, 매출접수분에 한함)인 회원에 한하여 제공됩니다.",
        "이 서비스의 이용기준은 매년 1월 1일~12월 31일로 산정되며, 카드회원 본인에 한하여 서비스를 이용하실 수 있습니다.",
        "이 서비스는 회원 상태가 정상인 회원님에 한하여 제공되며, 서비스 이용 횟수 초과 시 서비스를 이용하실 수 없습니다.",
        "프리미엄 베이커리 할인 서비스의 경우 와인 및 소매상품은 할인 대상에서 제외됩니다.(전 호텔 대상)",
        "특급호텔 레스토랑 할인 서비스 중 스위스 그랜드 호텔(구, 그랜드 힐튼 서울), 콘래드 호텔의 경우 음료 및 주류는 할인에서 제외됩니다.",
        "이 서비스는 다른 프로모션 및 혜택과 중복 사용이 불가능하며, 현금화 될 수 없습니다.",
        "국내 프리미엄 베이커리, 국내 특급호텔 뷔페, 레스토랑 할인 서비스는 대상 가맹점에서 택 1하여, 월 1회, 연 3회 이용하실 수 있으며, 결제 시 현장할인 됩니다.",
        "Shopping",
        "롯데면세점 5~15% 할인 서비스",
        "국내 제휴 명품 브랜드 할인 우대 혜택 서비스",
        "이용조건",
        "이 서비스는 엠비에이(MBA)카드 제시 후 혜택 받으실 수 있습니다."
      ]
    },
    {
      "type": "프리미엄 서비스",
      "summary": "비자 시그니처 서비스",
      "details": [
        "국내 주요 특급호텔 무료 발렛파킹 서비스 제공 (호텔별 월 5회)",
        "이용 방법",
        "주차 시 호텔 현관에서 도어맨에게 발렛파킹을 요청하면, 도어맨이 차량을 인도받고 주차티켓을 교부",
        "차량 인수 시 도어맨에게 주차티켓과 해당 카드를 제시",
        "도어맨이 소지한 단말기를 통해 서비스 이용 가능 여부 확인 후 서비스 제공",
        "서울 드래곤 시티는 복합호텔로서 아래의 4개 호텔 중 어느 호텔을 이용하시더라도 무료 발렛파킹 서비스를 이용하실 수 있습니다. (그랜드 머큐어 앰배서더 서울 용산, 노보텔 스위트 앰배서더 서울 용산, 노보텔 앰배서더 서울 용산, 이비스 스타일 앰배서더 서울 용산)",
        "서비스 제외기간",
        "힐튼 경주 : 신정, 구정, 추석 연휴기간, 벚꽃 시즌(4/2~4/16), 여름 성수기(7/19~8/31), 연말 연시(12/31)",
        "오크우드 프리미어 코엑스 센터의 경우 코엑스 내 전시 또는 행사 시 서비스가 제한될 수 있습니다.",
        "이용조건",
        "위 서비스는 지난 달 1일~ 말일까지 해당 카드 이용실적 70만원 이상 시(일시불/할부) 서비스가 제공됩니다.",
        "해당 카드를 최초로 발급하신 경우, 카드사용등록일로부터 다음 달 말일까지 해당 카드 이용실적이 10만원이상(일시불/할부)인 회원님에 한하여 서비스를 제공받으실 수 있습니다.",
        "지난 달 이용실적 산정 시 제외되는 금액: 단기카드대출(현금서비스), 장기카드대출(카드론), 주유업종 실적, 거래취소금액, 연회비, 이자 및 각종 수수료 등",
        "지난 달 실적 산정 시 본인카드와 가족카드의 이용실적을 합산한 금액을 기준으로 실적이 산정됩니다.",
        "교통(버스, 지하철, 하이패스 등) 이용 실적은 카드사에 접수된 이후 다음 달 초에 확정된 최종 금액에 대해서 해당 월의 실적에 반영되며, 해외 이용실적은 해외브랜드사로부터 카드사에 접수된 이후에 실적으로 반영됩니다.",
        "위 서비스는 해당 호텔의 객실 및 식음료업장(연회장 제외) 이용을 위해 내방한 회원 본인에 한해 제공함을 원칙으로 합니다.",
        "위 서비스 이용 시 호텔 정책에 따라 해당 호텔을 이용한 영수증 제시를 요청할 수 있으며, 영수증 미지참시에는 별도의 발렛파킹 비용과 주차금액이 청구될 수 있습니다.",
        "연회 참석 및 국가 주요행사 시에는 위 서비스를 이용하실 수 없으며, 이용고객의 집중으로 주차공간이 부족할 경우 서비스가 제한될 수 있습니다.",
        "서비스 제공 횟수를 초과하였을 경우 발렛파킹 비용을 별도로 부담하셔야 합니다.",
        "위 서비스 이용 시 발렛파킹 비용 및 1일 3시간 이내의 주차비가 무료로 제공됩니다. 이용시간 초과 시 주차금액이 별도로 부과될 수 있으며, 이는 별도로 부담하셔야 합니다.",
        "본인카드 및 가족카드 이용횟수를 합산하여 제공됩니다.",
        "레스케이프 호텔, 오크우드 프리미어 코엑스 센터, 쉐라톤 서울 팔래스 강남 호텔, JW 메리어트 동대문 스퀘어 서울, 대구 그랜드 호텔, 웨스틴 조선 부산 : 호텔 정책에 따라 당일 호텔 이용 영수증을 제시하는 경우에 한하여 무료, 발렛파킹 및 3시간 무료 주차 서비스가 제공되며, 영수증 미지참 시에는 발렛파킹 이용 요금과 주차요금 모두를 현장에서 지불하셔야 합니다.",
        "JW 메리어트 호텔 서울 : 호텔 정책에 따라 당일 호텔에서 2만 5천원 이상 이용한 영수증을 제시하는 경우에 한하여 3시간 무료 주차 서비스가 제공됩니다. 영수증 미지참 시에는 주차요금을 현장에서 지불 하셔야 합니다.",
        "인천공항 무료 발렛파킹 서비스 제공 (월 5회)",
        "이용방법",
        "이용조건",
        "위 서비스는 지난 달 1일~ 말일까지 해당 카드 이용실적 70만원 이상 시(일시불/할부) 서비스가 제공됩니다.",
        "해당 카드를 최초로 발급하신 경우, 카드사용등록일로부터 다음달 말일까지 해당 카드 이용실적이 10만원 이상(일시불/할부)인 회원님에 한하여 서비스를 제공받으실 수 있습니다.",
        "지난 달 이용실적 산정 시 제외되는 금액 : 단기카드대출(현금서비스), 장기카드대출(카드론), 주유업종 실적, 거래취소금액, 연회비, 이자 및 각종 수수료 등",
        "지난 달 실적 산정 시 본인카드와 가족카드의 이용실적을 합산한 금액을 기준으로 실적이 산정됩니다.",
        "교통(버스, 지하철, 하이패스 등) 이용 실적은 카드사에 접수된 이후, 다음 달 초에 확정된 최종 금액에 대해서 해당 월의 실적에 반영되며, 해외 이용실적은 해외브랜드사로부터, 카드사에 접수된 이후에 실적으로 반영됩니다.",
        "서비스 제공 횟수를 초과하였을 경우 발렛파킹 비용을 별도로 부담하셔야 합니다.",
        "발렛파킹 및 차량 출차 서비스는 24시간 제공됩니다.",
        "3층 여객터미널 승용차 전용 도로에서 5분 이상 정차 시는 과태료가 부과될 수 있습니다.",
        "위 서비스는 발렛파킹 비용에만 적용되므로, 주차비용은 별도로 정산하셔야 합니다.",
        "국가 주요행사 등 공항에서 정하는 규정에 따라 서비스가 제한될 수 있습니다.",
        "공항 이용객이 많은 성수기, 명절 기간 또는 공항 주차장 만차 시 서비스 이용이 제한될 수 있습니다. (성수기:7/15~8/31, 명절: 설날/추석)",
        "인천공항 제1여객터미널 발렛파킹 서비스는 ㈜하이파킹, 제2여객터미널 발렛파킹 서비스는 AJ파크에 의해 제공되니 서비스 이용 시 공식 주차대행 업체인지 확인 하시기 바랍니다.",
        "본인카드 및 가족카드 이용횟수를 합산하여 제공됩니다.",
        "김포공항 무료 발렛파킹 서비스 제공 (월 2회, 연 12회)",
        "이용방법",
        "이용조건",
        "위 서비스는 지난 달 1일~ 말일까지 해당 카드 이용실적 70만원 이상 시(일시불/할부) 서비스가 제공됩니다.",
        "해당 카드를 최초로 발급하신 경우, 카드사용등록일로부터 다음달 말일까지 해당 카드 이용실적이 10만원 이상(일시불/할부)인 회원님에 한하여 서비스를 제공받으실 수 있습니다.",
        "지난 달 이용실적 산정 시 제외되는 금액: 단기카드대출(현금서비스), 장기카드대출(카드론), 주유업종 실적, 거래취소금액, 연회비, 이자 및 각종 수수료 등",
        "지난 달 실적 산정 시 본인카드와 가족카드의 이용실적을 합산한 금액을 기준으로 실적이 산정됩니다.",
        "교통(버스, 지하철, 하이패스 등) 이용 실적은 카드사에 접수된 이후, 다음 달 초에 확정된 최종 금액에 대해서 해당 월의 실적에 반영되며, 해외 이용실적은 해외브랜드사로부터, 카드사에 접수된 이후에 실적으로 반영됩니다.",
        "발렛파킹 서비스 제공시간은 05:30~20:30이나, 차량 출차 서비스는 24시간 제공됩니다.",
        "서비스 제공 횟수를 초과하였을 경우 발렛파킹 비용을 별도로 부담하셔야 합니다.",
        "위 서비스는 발렛파킹 비용에만 적용되므로, 주차비용은 별도로 정산하셔야 합니다.",
        "국가 주요행사 등 공항에서 정하는 규정에 따라 서비스가 제한될 수 있습니다.",
        "공항 이용객이 많은 성수기, 명절 기간 또는 공항 주차장 만차 시 서비스 이용이 제한될 수 있습니다. (성수기:7/15~8/31, 명절: 설날/추석)",
        "본인카드 및 가족카드 이용횟수를 합산하여 제공됩니다.",
        "김해공항 무료 발렛파킹 서비스 제공 (월 2회, 연 12회)",
        "이용방법",
        "이용조건",
        "위 서비스는 지난 달 1일~ 말일까지 해당 카드 이용실적 70만원 이상 시(일시불/할부) 서비스가 제공됩니다.",
        "해당 카드를 최초로 발급하신 경우, 카드사용등록일로부터 다음달 말일까지 해당 카드 이용실적이 10만원 이상(일시불/할부)인 회원님에 한하여 서비스를 제공받으실 수 있습니다.",
        "지난 달 이용실적 산정 시 제외되는 금액: 단기카드대출(현금서비스), 장기카드대출(카드론), 주유업종 실적, 거래취소금액, 연회비, 이자 및 각종 수수료 등",
        "지난 달 실적 산정 시 본인카드와 가족카드의 이용실적을 합산한 금액을 기준으로 실적이 산정됩니다.",
        "교통(버스, 지하철, 하이패스 등) 이용 실적은 카드사에 접수된 이후 다음 달 초에 확정된 최종 금액에 대해서 해당 월의 실적에 반영되며, 해외 이용실적은 해외브랜드사로부터 카드사에 접수된 이후에 실적으로 반영됩니다.",
        "위 서비스 이용을 위해 반드시 출국일정 24시간 이전에 지정주차장으로 유선예약하셔야 하며, 예약 시 해당 카드 회원임을 반드시 미리 알려주셔야 합니다.",
        "위 서비스는 김해공항 지정주차장을 통해 제공되며, 무료 발렛파킹 서비스 이용 시 1일 주차 무료 서비스가 함께 제공됩니다.",
        "무료 서비스 제공 횟수를 초과하였을 경우, 발렛파킹 비용을 별도로 부담하셔야 합니다.",
        "무료 주차서비스는 1일간만 적용되며, 1일 이상 추가되는 주차비용은 별도로 정산하셔야 합니다.",
        "발렛파킹 및 차량 출차 서비스 제공시간은 06:30~22:00입니다.",
        "국가 주요행사 등 공항에서 정하는 규정에 따라 서비스가 제한될 수 있습니다.",
        "공항 이용객이 많은 성수기, 명절 기간 또는 공항 주차장 만차 시 서비스 이용이 제한될 수 있습니다. (성수기:7/15~8/31, 명절: 설날/추석)",
        "본인카드 및 가족카드 이용횟수를 합산하여 제공됩니다.",
        "비자 시그니처 서비스",
        "* TRAVEL, AIRPORT, HOTEL, SHOPPING 서비스는 국제 브랜드사인 VISA 자체 제공 서비스이며, 서비스 유효기간 경과 시 변동될 수 있습니다.",
        "* VISA SIGNATURE로 대상상품의 카드 발급 시 VISA SIGNATURE 등급의 국제브랜드 서비스가 제공됩니다.",
        "* VISA SIGNATURE 서비스의 유효기간은 2020년 1월 1일 ~ 2020년 12월 31일입니다.",
        "* 특급호텔/인천공항/김포공항/김해공항 발렛파킹 서비스는 VISA SIGNATURE 서비스 중 카드사(발급사) 선택 서비스로, 롯데카드 기준으로 제공됩니다.",
        "* VISA SIGNATURE 서비스 중 공항 라운지 서비스, 인천공항 무료 교통 서비스는 제공되지 않습니다."
      ]
    },
    {
      "type": "백화점",
      "summary": "롯데백화점 5% 현장할인 e-쿠폰",
      "details": [
        "롯데백화점 5% 현장할인 e-쿠폰",
        "쿠폰 발행월 직전 6개월간 롯데백화점에서 30만원 이상 신용구매(일시불, 할부) 이용회원에 한하여 매월 1일, 2매 제공",
        "* 세일상품, 식품, 식당, 가전, 명품매장 및 임대매장 등에서는 할인 적용 제외"
      ]
    },
    {
      "type": "면세점",
      "summary": "롯데면세점 5~15% 현장할인",
      "details": []
    },
    {
      "type": "테마파크",
      "summary": "롯데월드 본인종합이용권 50% 할인",
      "details": [
        "롯데월드 본인종합이용권 50% 할인",
        "월 1회, 연 6회, 현장 구매에 한해 적용"
      ]
    },
    {
      "type": "영화",
      "summary": "롯데시네마 관람권 1,500원 할인",
      "details": [
        "롯데시네마 영화관람료 1,500원 청구할인",
        "1일 1회, 월 5회, 연 12회, 현장 구매에 한해 적용"
      ]
    },
    {
      "type": "호텔",
      "summary": "롯데호텔 객실 및 일부 식음료장 할인",
      "details": [
        "롯데호텔 객실 및 일부 식음료장 할인",
        "패키지 상품 제외 및 다른 서비스 중복 적용 불가\n  * 롯데월드, 롯데시네마 할인서비스는 지난달(1일~말일) 카드이용실적(일시불, 할부) 20만원 이상 이용인 회원님께 제공됩니다.\n  * 롯데 신용카드 최초 신규 회원님은 발급 후 3개월 동안(최초 사용등록월 포함 3개월 차 말일까지) 실적 상관없이 이용할 수 있습니다.\n  * 기본, 가족회원 및 복수카드를 소지하는 경우, 카드 이용금액 및 이용횟수가 모두 합산되어 적용됩니다."
      ]
    },
    {
      "type": "패밀리레스토랑",
      "summary": "T.G.I.FRiDAY’S 10% 현장할인",
      "details": [
        "T.G.I.FRiDAY’S 10% 현장할인",
        "통신사 카드 및 여타 할인권과 중복이용 불가",
        "일 1회, 결제금액 기준 20만원(할인한도 2만원) 까지 할인",
        "* T.G.I.F, 미스터피자 할인서비스는 지난달(1일~말일) 카드이용실적(일시불, 할부) 20만원 이상 이용인 회원님께 제공됩니다.",
        "* 롯데 신용카드 최초 신규 회원님은 발급 후 3개월 동안(최초 사용등록월 포함 3개월 차 말일까지) 실적 상관없이 이용할 수 있습니다.",
        "* 기본, 가족회원 및 복수카드를 소지하는 경우, 카드 이용금액 및 이용횟수가 모두 합산되어 적용됩니다."
      ]
    },
    {
      "type": "푸드",
      "summary": "미스터피자 15% 현장할인,롯데리아·나뚜루·엔제리너스 1,000원당 50원 할인",
      "details": [
        "미스터피자 15% 현장할인",
        "월 3회, 연 12회, 일 결제금액 20만원까지 할인",
        "세트메뉴/할인쿠폰/통신사 및 타 카드할인 중복 불가",
        "리조트, 야구장 등 입점매장 제외(세부 매장은 홈페이지 참조)",
        "롯데리아·나뚜루·엔제리너스 1,000원당 50원 할인",
        "신용정보 마케팅 활용 동의 회원에 한하여 제공",
        "* T.G.I.F, 미스터피자 할인서비스는 지난달(1일~말일) 카드이용실적(일시불, 할부) 20만원 이상 이용인 회원님께 제공됩니다.",
        "* 롯데 신용카드 최초 신규 회원님은 발급 후 3개월 동안(최초 사용등록월 포함 3개월 차 말일까지) 실적 상관없이 이용할 수 있습니다.",
        "* 기본, 가족회원 및 복수카드를 소지하는 경우, 카드 이용금액 및 이용횟수가 모두 합산되어 적용됩니다."
      ]
    },
    {
      "type": "헤어",
      "summary": "박준 뷰티랩 20% 현장할인, 박승철 헤어스투디오 15% 현장할인",
      "details": [
        "박준 뷰티랩 20% 현장할인",
        "박승철 헤어스투디오 15% 현장할인 (프리미엄 박승철 매장 제외)",
        "프리미엄 매장, 드라이, 클리닉 물품판매 제외",
        "* 롯데 신용카드 최초 신규 회원님은 발급 후 3개월 동안(최초 사용등록월 포함 3개월 차 말일까지) 실적 상관없이 이용할 수 있습니다.",
        "* 기본, 가족회원 및 복수카드를 소지하는 경우, 카드 이용금액 및 이용횟수가 모두 합산되어 적용됩니다."
      ]
    },
    {
      "type": "기타",
      "summary": "L.POINT 제휴사 포인트 적립",
      "details": [
        "L.POINT 제휴사 포인트 적립",
        "L.POINT의 사용과 적립에 관한 자세한 내용은 L.POINT 홈페이지(www.lpoint.com) 참조",
        "SK주유포인트 적립 서비스가 제외됩니다."
      ]
    }
  ],
  "caution": [
    "유의사항",
    "* VISA SIGNATURE 서비스의 이용조건과 유의사항은 VISA 홈페이지(www.visakorea.com)를 통해 확인하시기 바랍니다.",
    "* 이 상품설명서는 회원이 발급받은 상품의 이용약관과 함께 교부되며, 기타 카드 이용과 관련한 유의사항은 발급받은 상품의 이용약관을 통해 확인하시기 바랍니다.",
    "추가적인 혜택(포인트 및 할인혜택 등)에는 제공조건 및 한도 등이 적용됩니다. 자세한 내용은 롯데카드 홈페이지(www.lottecard.co.kr)를 참고하시기 바랍니다.",
    "카드 이용시 제공되는 추가적인 혜택은 카드 신규 출시 이후 3년 이상 축소 · 폐지없이 유지됩니다.",
    "상기에도 불구하고, 다음과 같은 사유가 발생한 경우 카드사는 추가적인 혜택을 변경할 수 있습니다.",
    "① 카드사 또는 부가서비스 관련 제휴업체의 휴업 ·도산 ·경영위기, 천재지변, 금융환경의 급변 또는 그 밖에 이에 준하는 사유의 발생",
    "② 카드사가 추가적인 혜택 유지를 위해 노력했음에도 불구하고 제휴업체가 일방적으로 변경을 통보함에 따른 불가피한 변경",
    "(단, 다른 제휴업체를 통해 동종의 추가적인 혜택 제공이 가능한 경우는 제외)",
    "③ 카드 신규출시 이후 3년 이상 경과했고, 해당 카드의 수익성 유지가 어려운 경우",
    "카드사가 추가적인 혜택을 변경하는 경우에는 변경 사유, 변경 내용 등을 사유발생 즉시 홈페이지에 게시하고 개별 고지해드립니다. 특히 해당카드의 수익성 유지가 어려워 변경하는 경우에는 6개월 전부터 매월 개별 고지해 드립니다.",
    "개별고지 방법 : 카드대금청구서, 우편, 이메일, 문자메세지 중 하나",
    "카드를 해지한 후에도 관련 법령 및 내부 지침에 의거하여 회원의 정보가 일정기간 보존됩니다.",
    "결제일 카드대금 납부 : 결제계좌 개설기관의 영업 마감시간(16시) 이후 결제계좌에 입금된 금액은 개설기관의 사정에 따라 당일 출금되지 못하여 연체로 처리될 수 있으니 유의하시기 바랍니다. 자동납부 업무 마감시간 이후 무통장, 가상계좌 입금을 통해 당일 결제가 가능합니다.(세부내용 홈페이지/모바일 앱 참조)",
    "카드 신청 전 상품설명서 및 약관의 내용을 읽어보시기 바랍니다."
  ]
}