{
  "card_id": 1128,
  "card_url": "https://www.card-gorilla.com/card/detail/1128",
  "card_name": "DC Sweet 롯데카드",
  "issuer": "롯데카드",
  "inactive": false,
  "brands": [
    "Mastercard"
  ],
  "annual_fee": {
    "domestic": "국내전용 5,000원",
    "international": "해외겸용 5,000원"
  },
  "required_spending": null,
  "required_spending_amount": null,
  "benefits": [
    {
      "type": "카페/디저트",
      "summary": "스위트 할인서비스",
      "details": [
        "Sweet 할인",
        "전월 청구서상 이용금액 20만원 이상: 10%할인",
        "전월 청구서상 이용금액 40만원 이상: 20%할인",
        "전월 청구서상 이용금액 60만원 이상: 30%할인",
        "Sweet 할인 가맹점: 롯데리아, 엔제리너스, TGIF, 크리스피크림도넛, 나뚜루, 보네스뻬",
        "상기 이용금액기준은 전월 청구서상 ‘DC Sweet 롯데카드’ 이용금액(일시불,할부)에 따라 당월(1일~말일) 할인율 및 할인한도가 적용됩니다.(단, 단기카드대출(현금서비스) 및 장기카드대출(카드론) 제외)",
        "Sweet 할인은 1만원 이상 결제 건에 한해 청구할인 제공됩니다.",
        "Sweet 할인은 건당 최대 1.5만원 / 년 최대 12만원까지 청구할인 제공됩니다.",
        "Sweet 할인은 가맹점 L.POINT 제휴사 현장할인과 중복할인 적용됩니다.",
        "단, TGIF는 통신사카드와 중복할인 불가능합니다.",
        "할부 이용 시에는 이용일 기준으로 총 금액이 이용기준금액에 합산됩니다.",
        "카드발급 후 발급 월 포함하여 3개월 동안은 실적 관계없이 10% 할인 적용됩니다.",
        "대형마트, 휴게소 등 관련 사업장 내 임대 매장에 대해서는 할인적용에서 제외될 수 있습니다."
      ]
    },
    {
      "type": "멤버십포인트",
      "summary": "더블 포인트 적립 서비스",
      "details": [
        "Sweet 할인 가맹점에서 L.POINT 더블적립",
        "DC Sweet 카드로 Sweet 할인 가맹점에서 제품 구매시 L.POINT 한번 더 적립해드립니다.",
        "DC Sweet 카드로 L.POINT 제휴사에서 이용시 L.POINT 한번 더 적립",
        "L.POINT 제휴사 및 적립율은 롯데카드 홈페이지에서 확인 가능합니다."
      ]
    },
    {
      "type": "쇼핑",
      "summary": "롯데백화점, 면세점, 롯데닷컴 할인 롯데마트, 롯데슈퍼, 토이저러스 무이자할부",
      "details": [
        "롯데백화점 5% 할인e-쿠폰, 2~3개월무이자할부, 무료주차권제공",
        "쿠폰발행월 직전 6개월간 롯데백화점에서 30만원 이상 신용판매(일시불, 할부) 이용회원에 한해 매월 1일, 2매 제공",
        "롯데면세점 5% 현장할인",
        "신라아이파크면세점 10~15% 현장할인(일부 브랜드 제외)",
        "롯데닷컴 최고5% 할인, 3개월무이자할부(일부상품 제외)",
        "롯데마트, 롯데슈퍼, 토이저러스 2~3개월무이자할부"
      ]
    },
    {
      "type": "푸드",
      "summary": "롯데리아, 나뚜루, 엔제리너스, TGI 할인",
      "details": [
        "T.G.I FRiDAY’s 10% 할인(주류제외)",
        "지난달(1일~말일) 이용실적(일시불, 할부) 20만원 이상인 회원님께 제공",
        "일1회, 이용금액기준 20만원까지 / 장기카드대출(카드론)제외",
        "통신사 할인 및 다른 할인권과 중복 할인 불가합니다.",
        "롯데리아, 엔제리너스커피, 나뚜루 1,000원당 50원 할인"
      ]
    },
    {
      "type": "테마파크",
      "summary": "롯데월드 50% 할인",
      "details": [
        "롯데월드 본인 종합이용권 50% 할인",
        "지난달(1일~말일) 이용실적(일시불, 할부) 20만원 이상인 회원님께 제공",
        "1월~12월까지 월1회, 연6회 제공/장기카드대출(카드론)제외"
      ]
    },
    {
      "type": "영화",
      "summary": "롯데시네마 관람료 할인",
      "details": [
        "롯데시네마 관람료 1,500원 할인",
        "지난달(1일~말일) 이용실적(일시불, 할부) 20만원 이상인 회원님께 제공",
        "일 1회, 월 5회, 연 12회 제공, 현장구매에 한해 적용/장기카드대출(카드론)제외"
      ]
    },
    {
      "type": "기타",
      "summary": "멤버십포인트 적립",
      "details": [
        "L.POINT",
        "롯데멤버스(주) 고객정보에 동의하신 회원에 한하여 L.POINT 회원가입이 가능합니다.",
        "L.POINT는 L.POINT 제휴사 이용시 결제금액에 따라 적립받고 현금처럼 사용 가능한 포인트 입니다.",
        "L.POINT 회원 가입시 롯데카드가 제공하는 L.POINT 적립서비스가 제공됩니다.",
        "L.POINT의 사용과 적립에 관한 자세한 내용은 L.POINT 홈페이지(www.lpoint.com) 및 롯데카드홈페이지(www.lottecard.co.kr)에서 확인하실 수 있습니다.",
        "SK주유포인트",
        "SK주유소에서 주유시 리터당 50포인트 적립(1포인트=1원)",
        "한도: 결제금액기준 일30만원, 월 100만원",
        "적립기준: 최근3개월(이용일 2일전부터 92일간) 월평균 이용실적이 30만원 이상(장기카드대출(카드론)제외) 회원",
        "포인트사용: 최초 1만 포인트 이상 적립된 후부터, SK주유소에서 1포인트 단위로 사용 가능합니다.(유효기간5년)",
        "주유 적립액은 SK주유소가 통보한 휘발류가 기준이며, 휘발유, 등유, 경유의 주유 시에만 적립되며, LPG충전의 경우에는 제외됩니다.",
        "자세한 사항은 당사 홈페이지(www.lottecard.co.kr)에 안내되어 있습니다."
      ]
    }
  ],
  "caution": [
    "추가적인 혜택(포인트 및 할인혜택 등)에는 제공조건 및 한도 등이 적용됩니다. 자세한 내용은 롯데카드 홈페이지(www.lottecard.co.kr)를 참고하시기 바랍니다.",
    "카드 이용시 제공되는 추가적인 혜택은 카드 신규 출시 이후 3년 이상 축소 · 폐지없이 유지됩니다.",
    "상기에도 불구하고, 다음과 같은 사유가 발생한 경우 카드사는 추가적인 혜택을 변경할 수 있습니다.",
    "① 카드사 또는 부가서비스 관련 제휴업체의 휴업 ·도산 ·경영위기, 천재지변, 금융환경의 급변 또는 그 밖에 이에 준하는 사유의 발생",
    "② 카드사가 추가적인 혜택 유지를 위해 노력했음에도 불구하고 제휴업체가 일방적으로 변경을 통보함에 따른 불가피한 변경",
    "(단, 다른 제휴업체를 통해 동종의 추가적인 혜택 제공이 가능한 경우는 제외)",
    "③ 카드 신규출시 이후 3년 이상 경과했고, 해당 카드의 수익성 유지가 어려운 경우",
    "카드사가 추가적인 혜택을 변경하는 경우에는 변경 사유, 변경 내용 등을 사유발생 즉시 홈페이지에 게시하고 개별 고지해드립니다. 특히 해당카드의 수익성 유지가 어려워 변경하는 경우에는 6개월 전부터 매월 개별 고지해 드립니다.",
    "* 개별고지 방법 : 카드대금청구서, 우편, 이메일, 문자메세지 중 하나",
    "카드를 해지한 후에도 관련 법령 및 내부 지침에 의거하여 회원의 정보가 일정기간 보존됩니다.",
    "결제일 카드대금 납부 : 결제계좌 개설기관의 영업 마감시간(16시) 이후 결제계좌에 입금된 금액은 개설기관의 사정에 따라 당일 출금되지 못하여 연체로 처리될 수 있으니 유의하시기 바랍니다. 자동납부 업무 마감시간 이후 무통장, 가상계좌 입금을 통해 당일 결제가 가능합니다.(세부내용 홈페이지/모바일 앱 참조)",
    "카드 신청 전 상품설명서 및 약관의 내용을 읽어보시기 바랍니다."
  ]
}