{
  "card_id": 183,
  "card_url": "https://www.card-gorilla.com/card/detail/183",
  "card_name": "SolSol(쏠쏠)카드",
  "issuer": "NH농협카드",
  "inactive": false,
  "brands": [
    "Mastercard",
    "JCB"
  ],
  "annual_fee": {
    "domestic": "해외겸용 10,000원",
    "international": null
  },
  "required_spending": null,
  "required_spending_amount": null,
  "benefits": [
    {
      "type": "생활",
      "summary": "주요 12대 생활업종 3~12% 청구할인",
      "details": [
        "주요 12대 생활업종 3~12% 청구할인",
        "1그룹 (12%할인): 휘트니스/요가, 세탁, 반려동물 업종",
        "2그룹 (10%할인): 영화, 커피, 베이커리 업종",
        "3그룹 (5%할인): 편의점, 주유, 대중교통 업종",
        "4그룹 (3%할인): 온라인쇼핑, 통신, 외식 업종",
        "무이자할부서비스 이용시, 무이자할부 혜택이 제공되므로 할인서비스는 제공되지 않습니다.(무이자할부 행사 및 우수고객 서비스에 의한 무이자할부 지원 시에도 할인이 제외됩니다.",
        "상품권 구매(선불카드 구입, 충전 포함)는 할인서비스가 제공되지 않습니다.",
        "백화점, 할인점, 쇼핑몰 내 입점매장은 할인서비스가 제외될 수 있습니다.",
        "월별 통합 할인한도",
        "1그룹: 전월실적 30만원 이상 (3천원) / 전월실적 70만원 이상(6천원) / 전월실적 120만원 이상 (1만2천원)",
        "2그룹: 전월실적 30만원 이상 (3천원) / 전월실적 70만원 이상(6천원) / 전월실적 120만원 이상 (1만2천원)",
        "3그룹: 전월실적 30만원 이상 (2천원) / 전월실적 70만원 이상(4천원) / 전월실적 120만원 이상 (8천원)",
        "4그룹: 전월실적 30만원 이상 (2천원) / 전월실적 70만원 이상(4천원) / 전월실적 120만원 이상 (8천원)",
        "전월실적 30만원 이상 시 그룹 통합 월 1만원 할인한도",
        "전월실적 70만원 이상 시 그룹 통합 월 2만원 할인한도",
        "전월실적 120만원 이상 시 그룹 통합 월 4만원 할인한도",
        "전월실적 산정시 할인 대상 업종 이용액은 50% 반영됩니다.",
        "청구할인 서비스 적용 대상 업종 및 가맹점",
        "1그룹",
        "휘트니스 /요가: 종합스포츠센터/요가 업종, 세탁: 세탁소 업종, 반려동물: 애완동물/애완용품/동물병원 업종",
        "2그룹",
        "영화: CGV, 커피: 스타벅스/이디야, 베이커리: 파리바게뜨/파리크라상/던킨도너츠/배스킨라빈스",
        "3그룹",
        "편의점: 편의점 업종 (GS25/CU/세븐일레븐 등), 주유: SK에너지/NH-Oil, 대중교통: 버스/지하철 (후불교통 이용 건, 시외·고속버스 제외)",
        "4그룹",
        "온라인 쇼핑: 오픈마켓 (11번가/G마켓/옥션/인터파크), 통신: SK텔레콤/KT/LG U+ (단, 자동납부 신청 후 정상 결제 건), 외식: 일반음식점 업종 (단, 평일 11:00~14:00 이용 건 한정)"
      ]
    }
  ],
  "caution": [
    "서비스 이용조건",
    "카드사용등록일로부터 다음 달 말일까지는 전월 실적 미달시에도 최저한도 기준으로 서비스를 제공하며, 전월 실적 조건 달성시 해당 구간의 할인한도를 제공합니다.",
    "전월실적은 해당카드로 전월(1일~말일) 국내·외 일시불/할부 이용금액을 의미합니다.",
    "이용금액은 승인일 기준 이용금액을 의미합니다.",
    "해외이용액은 매출표 접수일 기준으로 적용됩니다.",
    "매출취소 발생시 취소 매출표 접수월 이용실적에서 차감됩니다.",
    "대학(대학원)등록금, 각종 세금 및 공과금, 우체국 우편요금, 사회보험(국민건강/국민연금/ 고용/산재), 아파트관리비, 도시가스요금, 전기요금, 상품권 및 선불카드류구매(충전 포함), 단기카드대출(현금서비스), 장기카드대출(카드론), 각종 수수료 및 이자, 연체료, 연회비, 거래취소금액, 포인트(전부/일부) 결제 시 포인트 사용분 등의 이용금액은 제외됩니다.",
    "교통카드 이용금액 및 통신료 자동이체금액은 매출표 접수일 기준으로 이용금액에 합산 적용됩니다.",
    "월간 할인한도가 제한된 서비스는 매월별(1일~말일) 카드 이용순서 기준으로 적용됩니다..",
    "가족카드의 경우 본인카드 이용실적과 합산되지 않으며, 카드별 이용실적을 각각 체크하여 서비스가 제공됩니다.",
    "카드서비스 적용은 NH농협카드 전산상 등록된 해당 가맹점·업종 이용액에 한합니다.",
    "해외 이용시 해외브랜드수수료와 해외이용수수료가 포함 청구됩니다.",
    "* 해외이용대금(a) : 해외이용금액(미화) × 접수일자의 1회차 전신환매도율",
    "* 해외브랜드수수료(b) : a × (W(JCB) 1%, Master 1%, UnionPay 0.6%)",
    "* 해외이용수수료 : (a + b) × 0.25%",
    "단, 해외브랜드 및 이용수수료는 해외브랜드사의 정책에 따라 변동될 수 있습니다.",
    "즉시결제 서비스는 제공되지 않습니다.",
    "카드이용 시 제공되는 포인트 및 할인혜택 등의 부가서비스는 카드 신규출시(2017년 4월 27일) 이후 3년 이상 축소·폐지없이 유지됩니다.",
    "상기에도 불구하고, 다음과 같은 사유가 발생한 경우 카드사는 부가서비스를 변경할 수 있습니다.",
    "* 카드사 또는 부가서비스 관련 제휴업체의 휴업·도산·경영위기, 천재지변, 금융환경 급변 도는 그 밖에 이에 준하는 사유의 발생",
    "* 카드사의 노력에도 제휴업체가 일방적으로 부가서비스 변경을 통보(단, 다른 제휴업체를 통해 동종의 유사한 부가서비스 제공이 가능한 경우 제외)",
    "카드 신규 출시 이후 3년 이상 경과했고, 해당 카드의 수익성 유지가 어려운 경우",
    "카드사가 부가서비스를 변경하는 경우에는 부가서비스 변경 사유, 변경 내용 등을 사유발생 즉시 홈페이지에 게시하고, 사전 또는 사후 개별 고지해 드립니다. 특히 카드 신규 출시 이후 3년 이상 경과했고, 해당 카드의 수익성 유지가 어려워 부가서비스를 변경하는 경우에는 6개월 전부터 매월 개별고지 해드립니다.",
    "개별고지방법 : 이용대금명세서, 우편, 전자우편(e-mail), 휴대폰 문자메시지 중 하나"
  ]
}