{
  "card_id": 717,
  "card_url": "https://www.card-gorilla.com/card/detail/717",
  "card_name": "그랑블루 1st",
  "issuer": "우리카드",
  "inactive": "신규발급이 중단된 카드입니다.",
  "brands": [
    "BC",
    "Mastercard"
  ],
  "annual_fee": {
    "domestic": "국내전용 100,000원",
    "international": "해외겸용 100,000원"
  },
  "required_spending": null,
  "required_spending_amount": null,
  "benefits": [
    {
      "type": "적립",
      "summary": "[고액 적립] 최대 1.5% 적립",
      "details": [
        "[고액 적립] 최대 1.5% 적립",
        "국내 건당 300만원 이상 결제 시 1.5% 적립",
        "국내 건당 150만원 이상 결제 시 1.2% 적립",
        "국내 건당 50만원 이상 결제 시 1.0% 적립",
        "※ 월 한도: 고액적립, 특별적립 통합 30만점",
        "※ 전월 이용 실적 조건 없음",
        "※ 적립률 높은 순으로 우선 적용(단, 월 적립한도 초과 시, 기본 적립으로 적용)",
        "※ 고액 적립, 특별 적립, 기본 적립 간 중복 적용 불가"
      ]
    },
    {
      "type": "적립",
      "summary": "[특별 적립] 해외, 면세점, 백화점, 이동통신, 병의원, 4대 보험료 최대 2% 적립",
      "details": [
        "[특별 적립]",
        "해외, 면세점 2% 적립",
        "해외 : 해외직구 등 온라인결제 포함",
        "* 해외 결제 시 별도의 수수료가 발생할 수 있으며, 해당 내용은 ‘해외이용 안내’ 참조",
        "면세점 : 온라인 결제 포함",
        "백화점, 이동통신, 병의원 1.5% 적립",
        "백화점 : 신세계 백화점, 롯데 백화점, 현대 백화점 ※ 온라인 결제 적립 제외",
        "이동통신 : SKT, KT, LGU+, CJ헬로모바일, KTM모바일, U+알뜰 모바일",
        "* 휴대전화 요금에 한하며, 본 카드로 자동이체 신청 후 결제한 건에 대해서만 적립",
        "* 인터넷, 유선전화 등 결합상품 신청 시에는 적립 제외",
        "병의원 : 동물병원 제외",
        "4대 보험료(건강보험, 고용보험, 산재보험, 국민연금) 0.8% 적립",
        "4대 보험 : 건강보험, 고용보험, 산재보험, 국민연금",
        "* 본 카드로 자동이체 신청 후 결제한 건에 대해서만 적립 제공",
        "※ 월 한도: 고액적립, 특별적립 통합 30만점",
        "※ 전월 이용 실적 조건 없음",
        "※ 적립률 높은 순으로 우선 적용(단, 월 적립한도 초과 시, 기본 적립으로 적용)",
        "※ 고액 적립, 특별 적립, 기본 적립 간 중복 적용 불가"
      ]
    },
    {
      "type": "적립",
      "summary": "[기본적립] 특별 적립 외 국내 적립 대상 가맹점 0.5% 적립 [보너스적립] 12개월마다 20,000점 적립",
      "details": [
        "[기본적립] 특별 적립 외 국내 적립 대상 가맹점 0.5% 적립",
        "전월 이용 실적 조건 없음",
        "적립 한도: 무제한",
        "적립률 높은 순으로 우선 적용(단, 월 적립한도 초과 시, 기본 적립으로 적용)",
        "고액 적립, 특별 적립, 기본 적립 간 중복 적용 불가",
        "[보너스적립] 12개월마다 20,000점 적립",
        "발급월 포함 12개월 간 본인카드로 국내 가맹점 1천만원 이상 이용 시 보너스 포인트 제공",
        "적립일 : 대상기간 만료월 다음달 15일 (휴일일 경우 다음 영업일)",
        "* 적립일 기준 그랑블루 1st 카드가 해지된 경우 적립 불가",
        "* 본인카드와 별도로 가족카드로 상기 조건 충족 시에도 본인 회원에게 보너스 포인트 제공",
        "* 무이자할부 이용금액은 대상 매출액에서 제외"
      ]
    },
    {
      "type": "바우처",
      "summary": "프리미엄 기프트 5만원 상당 제공(연 1회, 택 1)",
      "details": [
        "프리미엄 기프트(연 1회, 택 1)",
        "1. 신세계 상품권 모바일 교환권 5만원",
        "신세계 상품권 모바일 교환권 5만원을 드립니다.",
        "전국 신세계백화점 상품권샵 또는 전국 이마트 매장 내 설치된 키오스크(무인 상품권 교환기)에서 신세계 상품권(지류권)으로 교환",
        "유효기간 : 교환권 - 발송일로부터 180일 / 상품권 - 발행일로부터 5년",
        "* 본 모바일 교환권은 매장에서 바로 이용 가능한 상품권이 아니므로, 반드시 지정 상품권샵/키오스크에서 신세계 상품권으로 교환 후 이용",
        "* 교환 불가 지점 : 신세계백화점 천안터미널점",
        "* 본 모바일 교환권에 표기된 유효기간(발송일로부터 180일) 이내에 상품권으로 교환해야 하며, 교환 유효기간 경과 후에는 소멸 처리되어 상품권으로 교환 및 환불 불가",
        "* 본 교환권은 비매품으로 환불, 현금 교환 및 매매될 수 없으며, 타인 양도 불가",
        "* 고객님의 부주의로 인한 유효기간 경과, 분실, 멸실, 훼손 시 재발행은 불가",
        "* 모바일 교환권 관련 문의 : 1599-4500",
        "2. 모바일 문화상품권 5만원",
        "모바일 문화상품권 5만원을 드립니다.",
        "CGV, 교보문고, CU, GS25, 미니스톱, 이마트 24에서 모바일 문화상품권을 제시하여 해당금액만큼 결제",
        "유효기간 : 발송일로부터 180일",
        "* 본 모바일 문화상품권은 매장에서 바로 이용 가능한 상품권이며, 유효기간 내 분할 사용 또는 가맹점 간 교차 사용 가능",
        "* 사용 불가 지점 : 일부 한강 편의점 및 고속도로 편의점",
        "* 본 모바일 문화상품권에 표기된 유효기간(발송일로부터 180일) 이내에 상품권으로 사용해야 하며, 사용 유효기간 경과 후에는 사용 및 환불 불가",
        "* 본 모바일 문화상품권은 비매품으로 환불, 현금 교환 및 매매될 수 없으며, 타인 양도 불가",
        "* 고객님의 부주의로 인한 유효기간 경과, 분실, 멸실, 훼손 시 재발행은 불가",
        "* 모바일 문화상품권 관련 문의 : 1599-4500",
        "3. 스마일캐시 5만원",
        "스마일캐시 5만원을 드립니다.",
        "G마켓, 옥션, G9 및 스마일페이에서 캐시 등록 후 제휴 가맹점에서 사용",
        "유효기간 :등록 유효기간 발송일로부터 180일 / 등록 후 캐시 유효기간 - 5년",
        "* 모바일 교환권은 매장에서 바로 이용 가능한 상품권이 아니므로, 반드시 캐시 등록 후 이용",
        "* 본 모바일 교환권에 표기된 유효기간(발송일로부터 180일) 이내에 상품권으로 교환해야 하며, 교환 유효기간 경과 후에는 교환 및 환불 불가",
        "* 본 교환권은 비매품으로 환불, 현금 교환 및 매매될 수 없으며, 타인 양도 불가",
        "* 고객님의 부주의로 인한 유효기간 경과, 분실, 멸실, 훼손 시 재발행은 불가",
        "* 모바일 교환권 관련 문의 :☎ 1599-4500",
        "이용조건 : 국내 모든 가맹점 이용액 초년도 30만원, 2차년도부터는 전년도 또는 당해년도 200만원 이상 이용 시 선택가능 (연회비 납부 필수)",
        "대상기간 : 카드 발급월 포함 12개월 (예 : 2021년 4월 10일 발급 ~ 2022년 3월 31일까지)",
        "* 바우처 유효기간 경과 / 분실 / 멸실 / 훼손 시 재발행 불가",
        "* 바우처 변경 / 교환 / 취소 및 타 할인카드 / 쿠폰과 중복사용 불가",
        "* 본인회원이 ☎1599-2600(우리카드 프리미엄 전용 상담데스크)로 신청 시 제공(가족카드는 기프트 신청 불가)"
      ]
    },
    {
      "type": "프리미엄 서비스",
      "summary": "전세계 공항 라운지 무료 이용 서비스 국내 지정 골프장 무료 커피 제공(골프장 카페 서비스), 골프연습장 무료 제공(골프연습장 타석 서비스)",
      "details": [
        "[그랑블루 1st 프리미엄 서비스]",
        "본 서비스는 더 라운지 멤버스(The Lounge Members) 앱 설치 후 이용 가능",
        "통합 월 1회, 연 5회 제공",
        "* MasterCard 브랜드만 제공(국내전용(BC) 브랜드 제공 불가)",
        "* 전월 국내 가맹점 이용금액 50만원 이상 시 무료 제공(단, 카드수령 등록일 (사용개시일 포함)로부터 다음달 말일까지는 국내 가맹점 50만원 이상 이용 시 그 다음날부터 무료 제공)",
        "* 이용 가능 라운지/골프장/골프연습장은 더 라운지 멤버스 앱 또는 홈페이지(www.theloungemembers.com) 참조",
        "* 문의처: 더 라운지 멤버스 고객센터 02-2664-7436(+82-2-2664-7436), 고객센터 운영시간(한국시간 기준) 평일 09:00~18:00 (점심시간 12:00~13:00 제외)",
        "1. 전세계 공항 라운지 무료 이용 서비스",
        "회원가입 ▶ 로그인 ▶ 카드등록 ▶ 이용인원 선택 ▶ 라운지 이용권 받기",
        "라운지 입장 시 라운지 이용권과 여권, 당일 출발 항공권 제시",
        "라운지 무료 이용 가능여부 확인 후 무료 입장 (카드소비자 본인 입장 필수)",
        "* 본인 회원 1인 한정 (동반인 무료입장 불가)",
        "* 라운지 이용권은 발급 후 24시간 동안 유효하며, 기간 내 미사용 시 자동 취소 (취소 후에는 다시 재발급 가능)",
        "* 취소된 라운지 이용권은 이용 가능 횟수에서 차감되지 않음",
        "2. 국내 지정 골프장 무료 커피 제공(골프장 카페 서비스)",
        "회원가입 ▶ 로그인 ▶ 신용/체크카드 ▶ 카드등록 ▶ 마스터카드번호 입력 ▶ 카페 이용권 받기",
        "골프장 내장시 라운딩 전, 클럽하우스 레스토랑 또는 스타트하우스에서 이용권 제시",
        "카페 서비스 이용 가능여부 확인 후 커피(4잔) 제공)",
        "* 카페 이용권은 발급 후 24시간 유효하며, 마이페이지 이용권 보관함에 자동 저장되어 미 사용 시 취소 (미 사용 이용권은 재발급 가능)",
        "3. 국내 지정 골프연습장 무료 제공(골프연습장 타석 서비스)",
        "회원가입 ▶ 로그인 ▶ 신용/체크카드 ▶ 카드등록 ▶ 마스터카드번호 입력 ▶ 연습장 이용권 받기",
        "골프연습장 내장후 골프연습장 내 키오스크에서 타석 배정하기(시간 & 타석 선택 ▶ 일일고객 선택 ▶ 제휴사 고객 선택 ▶ 이용권 QR코드 스캔 ▶ 타석 배정표 출력)",
        "연습장 무료 이용 가능여부 확인 후 타석 이용",
        "* 타석 이용권은 1일 1회 무료 이용 가능하며, 이용 시간은 60분 제공 (연습장 상황에 따라 변동될 수 있음)",
        "* 무료 타석 서비스는 키오스크를 통해서만 이용 가능하고, 본 이용권은 현금으로 교환되지 않음"
      ]
    },
    {
      "type": "주유",
      "summary": "SK 주유 및 충전 시 리터(ℓ)당 60원 청구 할인",
      "details": [
        "SK 주유 및 충전 시 리터(ℓ)당 60원 청구 할인",
        "통합 일 1회, 결제 건당 최대 할인 대상 금액 10만원,통합 월 30만원 한도",
        "할인금액 산정방법 = (주유 이용금액 / SK에너지 휘발유 공시가)X 리터(ℓ)당 할인금액(60원)",
        "휘발유, 경유, LPG 모두 할인(SK에너지 휘발유 공시가 환산 적용)",
        "전월 국내 가맹점 이용금액 50만원 이상 시 제공"
      ]
    },
    {
      "type": "여행/숙박",
      "summary": "국내 호텔/리조트/카라반/글램핑 2박 연박 시 1박 무료 해외 패키지 여행 할인 등 제공",
      "details": [
        "여행 지원 서비스",
        "국내 호텔/리조트/카라반/글램핑 2박 연박 시 1박 무료",
        "* 일반룸 기준,연휴 및 성수기 제외,주중 + 주말 예약 시 주말요금 고객부담, 연 1회 제공",
        "* 이용 가능한 가맹점은 우리카드 홈페이지(www.wooricard.com)에서 확인 가능하며, 마감 시 예약이 어려울 수 있음",
        "해외 패키지 여행 할인",
        "국내외 호텔 및 콘도 5~10% 할인",
        "제주도 렌터카 24H 무료 제공",
        "* 48H 이상 연속 이용 시 24H 무료 제공(월 1회)",
        "* 7~8월 성수기 제외",
        "* 국산차(K5 등급)에 한함",
        "KTX승차권 10% 할인(일반석, 본인한정, 통합 연2회)",
        "* 연휴 및 명절 특별 수송기간 제외",
        "국내 섬여행 (울릉도, 독도 등) 5%할인",
        "※  전월 국내 가맹점 이용금액 50만원 이상 시 제공",
        "※ 여행 지원 서비스는 ☎ 1661-7730 예약 시에만 제공",
        "※ 여행 지원 서비스의 상세 혜택 및 이용조건은 우리카드 홈페이지 참조"
      ]
    },
    {
      "type": "기타",
      "summary": "개인사업자 Win-Tax 서비스",
      "details": [
        "개인사업자 Win-Tax 서비스",
        "부가세 환급지원",
        "* 신용카드 매입내역의 공제/공제제외 자동분류",
        "* 부가세 환급 예상액 및 전자신고파일 자동 생성",
        "* 신용카드 매출전표 수집 불필요(5년간 조회 및 인쇄가능)",
        "전자세금계산서 발행",
        "* 전자세금계산서 무료 발행 및 SMS 전송",
        "* 거래명세표와 연동 발행 및 파일첨부 기능",
        "매출/매입 통합관리",
        "* 세금계산서, 신용카드, 현금영수증의 전체 매출 내역 자동 간편조회",
        "* 기간별 매입 요약정보를 통해 효율적인 비용관리",
        "세무 통합 관리",
        "* 합계표, 신고서 등 세무증빙자료 생성",
        "* 면세 농수산물 구매에 대한 의제매입세액공제 지원",
        "세무상담",
        "* 24시간 온라인 세무상담 지원 (www.win-tax.co.kr)",
        "서비스 이용방법",
        "신청대상",
        "* 그랑블루 1st 카드를 소지한 개인사업자 고객",
        "신청방법",
        "* 필요서류 구비 후 우리은행 영업점 및 우리카드 영업소 방문을 통해 신청 가능",
        "* 우리카드 Win-Tax 가입신청서, 사업자등록증(대표자 본인 방문 필수)",
        "회원인증(그랑블루 1st 카드를 수령 2영업일 후 부터 회원인증 가능)",
        "* 우리카드 Win-Tax(www.win-tax.co.kr)접속하여 회원 인증 후 이용(전자세금용/사업자용 공인인증서 또는 대표자 명의 휴대전화번호 준비)",
        "그랑블루 1st 카드를 1회 이상 이용 시 서비스 제공",
        "우리카드 세무지원 고객센터 ☎ 1577-0174 (평일09:00~18:00)"
      ]
    }
  ],
  "caution": [
    "프리미엄 기프트 서비스 유의사항",
    "유의사항",
    "부가서비스 안내",
    "카드 이용 시 제공되는 포인트 및 할인혜택 등의 부가서비스는 카드 신규 출시(2021년 2월 15일) 이후 3년 이상 축소·폐지 없이 유지됩니다.",
    "상기에도 불구하고, 다음과 같은 사유가 발생한 경우 카드사는 부가서비스를 변경할 수 있습니다.",
    "* 카드사 또는 부가서비스 관련 제휴업체의 휴업·도산·경영위기, 천재지변, 금융환경 급변 또는 그 밖에 이에 준하는 사유의 발생",
    "* 카드사의 노력에도 제휴업체가 일방적으로 부가서비스 변경을 통보 (단, 다른 제휴업체를 통해 동종의 유사한 부가서비스 제공이 가능한 경우 제외)",
    "* 카드 신규출시 이후 3년 이상 경과했고, 해당 카드의 수익성 유지가 어려운 경우",
    "카드사가 부가서비스를 변경하는 경우에는 부가서비스 변경 사유, 변경 내용 등을 사유발생 즉시 홈페이지에 게시하고, 대금청구서, 우편서신, 전자우편(E-MAIL), 휴대폰 문자메시지 서비스 또는 그밖에 이와 유사한 방법 중 1가지 이상의 방법으로 고지하여 드립니다. 특히 카드 신규 출시 이후 3년 이상 경과했고, 해당 카드의 수익성 유지가 어려워져 부가서비스를 변경하는 경우에는 6개월 전부터 매월 개별고지 해드립니다.",
    "* 개별고지 방법 : 카드대금청구서, 우편서신, 전자우편(E-MAIL), 휴대폰 문자메시지 서비스 또는 그 밖에 이와 유사한 방법 중 어느 하나",
    "실적 산정 방법 안내",
    "전월실적은 전월 1일부터 말일(매출승인일 기준)까지 카드별 국내 가맹점 이용실적이며, 교통카드 이용금액 및 통신료 자동이체 금액은 매출표 접수일기준으로 해당월 이용금액에 합산 적용됩니다.",
    "해외가맹점 이용금액, 단기카드대출 (현금서비스), 장기카드대출(카드론), 수수료, 이자, 연회비는 전월실적에 포함되지 않습니다.",
    "할인서비스 등 부가서비스의 월한도/횟수 제한은 전월 이용실적에 따라 당월 1일~말일까지 적용됩니다. 단, 서비스 제공은 거래(매입) 순서대로 적용됩니다.",
    "취소 매출은 취소매출표 접수월 이용실적에서 차감합니다. (단, 국내 가맹점 취소 매출이 매월 1~2일 사이에 접수된 경우 전월 이용실적에서 차감합니다.)",
    "* 예) 1월 31일 이용건 취소 시 2월 2일까지 취소매출표가 카드사에 접수된 경우에는 1월 이용실적에서 차감, 이후 접수된 경우는 2월 이용실적에서 차감",
    "카드수령 등록일(사용개시일 포함)로부터 다음달 말일까지는 이용실적 조건없이 서비스가 적용됩니다. (단, 그랑블루 1st 프리미엄 서비스는 카드수령 등록일(사용개시일 포함)로부터 다음달 말일까지 국내 가맹점 이용금액 50만원 이상 시, 그 다음날부터 서비스 제공)",
    "해외이용 안내",
    "해외 이용 시(해외사이트 거래 포함) 미화(USD)기준 거래미화금액에 접수일의 우리은행 최초고시 전신환 매도율을 적용한 후, 국제브랜드사가 부과하는 국제브랜드 수수료 1%와 우리카드가 부과하는 해외서비스 수수료(0.3%)를 포함하여 원화로 청구됩니다.",
    "ATM 예금인출 시에는 인출금액에 대한 미화 환산금액에 국제브랜드 수수료 1%와 거래건당 $3의 해외예금인출 수수료를 포함하여 현금인출 시점의 우리은행 최초고시 전신환 매도율을 적용한 금액이 출금됩니다.",
    "해외에서 원화로 결제 시, 해외 가맹점에서 현지통화를 원화로 전환하는 과정에서 추가 수수료를 부과하는 경우가 있으니 해외에서는 원화가 아닌‘현지통화’로 결제하시길 권장해드립니다. (우리카드 홈페이지 ▶ 이용안내 ▶ 해외이용가이드 ▶ 해외이용안내 참고)",
    "해외원화결제차단 서비스 설정 방법",
    "* 우리카드 홈페이지/모바일앱/모바일웹 : MY ▶ 해외이용설정 ▶ 해외이용 등록/해제▶ 해외사용정지 ▶ 해외원화결제차단",
    "국가별 상황에 따라 일부 가맹점 및 ATM에서 단기카드대출(현금서비스)이용이 어려울 수 있으니, 대체 결제수단을 소지하시기 바랍니다.",
    "해외 이용시 청구금액 산출방법",
    "* 해외 이용시 청구금액 = (거래미화금액×전신환 매도율①) + 국제브랜드 수수료② + 해외서비스 수수료③",
    "① 전신환 매도율 : 접수일의 우리은행 최초고시 전신환 매도율",
    "② 국제브랜드수수료 = (거래미화금액 × 국제브랜드 이용수수료율 1%) × 전신환 매도율",
    "③ 해외서비스 수수료 = (거래미화금액 × 해외서비스 수수료율 0.3%) × 전신환 매도율",
    "일부 해외 가맹점 거래 시 IC칩 비밀번호(PIN)를 요구하는 경우가 있으므로 출국 전 반드시 IC칩 비밀번호(PIN) 등록 여부를 확인하시기 바랍니다.",
    "일부 비표준화된 해외 가맹점 및 ATM은 비밀번호(PIN) 입력시 6자리를 요구할 수도 있습니다. ‘카드비밀번호 4자리 + 00’을 입력하여 사용하시기 바랍니다."
  ]
}