{
  "card_id": 1017,
  "card_url": "https://www.card-gorilla.com/card/detail/1017",
  "card_name": "신세계 신한카드 SKYPASS / Asiana Club",
  "issuer": "신한카드",
  "inactive": false,
  "brands": [
    "Mastercard",
    "UnionPay"
  ],
  "annual_fee": {
    "domestic": "해외겸용 42,000원",
    "international": null
  },
  "required_spending": null,
  "required_spending_amount": null,
  "benefits": [
    {
      "type": "멤버십포인트",
      "summary": "신세계백화점 멤버십, 신세계 포인트 적립",
      "details": [
        "신세계백화점 멤버십과 신세계포인트 적립",
        "일반 고객기준 3~5% 신세계백화점 할인쿠폰 제공(월 최대 6매, 일부품목제외)",
        "신세계포인트 가맹점 이용시 신세계포인트 적립(신세계백화점 0.2%, 이마트 등 0.1%)",
        "할인쿠폰 수량 및 할인품목, 제외상품은 신세계백화점 정책에 따라 변경될 수 있습니다.",
        "매월 신세계백화점 무료주차권 2매 발송(1일 1회, 2시간)",
        "신세계백화점 멤버십 및 신세계포인트는 제휴사의 정책을 따릅니다.",
        "신세계멤버십 및 신세계포인트 서비스의 자세한 내용은 신세계 백화점 홈페이지(http://deptmapp.shinsegae.com/custsvc/ssgCardinfo.jsp) 및 신세계포인트 홈페이지(www.shinsegaepoint.com)를 참고 바랍니다."
      ]
    },
    {
      "type": "항공마일리지",
      "summary": "대한항공: 기본적립 및 추가적립 1,500원당 1마일 아시아나: 기본적립 및 추가적립 1,000원당 1마일",
      "details": [
        "대한항공 마일리지/아시아나항공 마일리지(택1)",
        "대한항공",
        "전 가맹점 일시불, 할부 이용액 1.500원당 1마일리지 적립",
        "아시아나항공",
        "전 가맹점 일시불, 할부 이용액 1천원당 1마일리지 적립",
        "마일리지 적립 세부 안내를 참조하시기 바랍니다.",
        "항공 마일리지 적립은 전월 실적과 관계없이 제공됩니다.",
        "항공 마일리지 추가 적립",
        "조건: 신세계백화점에서 당월 1일~말일(승인시점 기준) 30만원 이상 이용 시",
        "* 단, 신세계백화점 온라인몰 및 별도 임대매장에서의 거래는 조건 기준에서 제외됩니다.",
        "적립대상: 당월 1일~말일 이용한 30만원 초과 일시불+할부 이용금액을 대상으로 마일리지 추가 적립",
        "대한항공: 1,500원당 1마일리지 추가 적립(월 200마일리지 한정)",
        "아시아나항공: 1천원당 1마일리지 추가 적립(월 300마일리지 한정)",
        "마일리지 적립 세부 안내를 참조하시기 바랍니다.",
        "마일리지 적립 세부 안내",
        "항공 마일리지 적립은 마일리지 적립대상의 총 청구금액에 대해 단위금액(대한항공 1,500원/아시아나 1천원)으로 나눈 후 단위금액 미만은 반올림하여 카드대금 결제일에 적립됩니다.",
        "단, 항공마일리지 추가적립은 실적조건이 만족된 해당월 거래시점[승인시점] 1일~말일까지의 사용액에 대하여 익월 말일까지 별도 적립됩니다.",
        "아래 경우는 마일리지가 적립되지 않습니다.",
        "* 연회비, 단기카드대출(현금서비스), 장기카드대출(카드론), 지방세납부(홈페이지, 창구납부 등 모든 지방세 납부 포함), 각종 수수료 및 이자, 선불카드(Gift카드 구매 포함) 충전금액, 당사 할인이 적용된 거래, 무이자할부 이용 거래, 거래 취소 금액 마일리지 추가 적립을 위한 신세계백화점 이용 거래 기준은 신세계백화점(온라인몰, 임대매장 제외)에서 거래하신 일시불 및 할부금액의 합산 기준입니다.",
        "마일리지 적립 대상매출이 아닌 매출은 추가마일리지도 적립되지 않습니다.",
        "해외거래 및 후불교통카드 매출의 경우 해당 거래의 전표 매입월기준으로 적립됩니다.",
        "항공마일리지 사용/소멸 정책은 항공사의 마일리지 운영 기준을 따릅니다.",
        "서비스 적용 기준",
        "결제일 할인 서비스는 승인 순서에 따라 적용됩니다.",
        "월 할인 및 적립 한도는 승인시점 기준으로 산정됩니다."
      ]
    },
    {
      "type": "해외이용",
      "summary": "면세/해외 할인",
      "details": [
        "면세/해외 할인",
        "신세계면세점 시내점 5% 결제일 할인",
        "* 월 최대 1만원 할인, 전월실적 불필요, 인터넷 및 공항점 제외",
        "해외 매출 5% 캐시백(단, 해외온라인거래는 제외)",
        "* 신세계 신한카드 SKYPASS/Asiana Club 카드로 연간 일시불+할부 1천만원 이상 이용시 제공",
        "* 연간 해외 일시불 이용액의 5% 캐시백(최대 5만원)",
        "* 연간기준: 1월~12월",
        "* 캐시백: 연1회 매년 2월 마지막주 캐시백 제공"
      ]
    },
    {
      "type": "프리미엄",
      "summary": "국제브랜드사 서비스",
      "details": [
        "국제브랜드사 서비스 공통사항 안내",
        "국제브랜드사 서비스에 대하여 보다 상세한 안내를 원하시는 고객님께서는 국제브랜드사별 홈페이지를 참조해 주시기 바랍니다.",
        "* 비자 홈페이지: www.visakorea.com",
        "* 마스터카드 홈페이지: www.mastercard.co.kr",
        "* 아멕스 홈페이지: www.americanexpress.co.kr",
        "* JCB(URS) 홈페이지: www.jcbcard.kr",
        "* UPI 홈페이지: www.unionpayintl.com/kr",
        "브랜드사 선택서비스는 각 브랜드사별 홈페이지 안내사항과 제공 내용이 상이할 수 있어, 당사에서 제공되는 서비스 가이드북 안내(제공처, 제공횟수 및 전월실적 조건 등)를 확인하시기 바랍니다.(브랜드사 홈페이지에 안내된 제공처라 하더라도 당사에서 안내된 제공처가 아닌 경우 서비스가 제공되지 않습니다.)",
        "브랜드별 홈페이지 서비스 안내사항 중 대상 등급 서비스가 아닌 경우 서비스 제공이 제한될 수 있습니다."
      ]
    }
  ],
  "caution": [
    "부가서비스 변경가능 사유",
    "카드 이용 시 제공되는 포인트 및 할인혜택 등의 부가서비스는 카드 신규출시(2017.04.01) 이후 3년 이상 축소·폐지 없이 유지 됩니다.",
    "상기에도 불구하고, 다음과 같은 사유가 발생한 경우 카드사는 부가서비스를 변경할 수 있습니다.",
    "① 카드사 또는 부가서비스 관련 제휴업체의 휴업·도산·경영위기, 천재지변, 금융환경 급변 또는 그 밖에 이에 준하는 사유의 발생",
    "② 카드사의 노력에도 제휴업체가 일방적으로 부가서비스 변경을 통보(단, 다른 제휴업체를 통해 동종의 유사한 부가서비스 제공이 가능한 경우 제외)",
    "③ 카드 신규출시 이후 3년 이상 경과했고, 해당 카드의 수익성 유지가 어려운 경우",
    "카드사가 부가서비스를 변경하는 경우에는 부가서비스 변경 사유, 변경 내용 등을 사유발생 즉시 홈페이지에 게시하고, 개별 고지해 드립니다. 특히 카드 신규 출시 이후 3년 이상 경과했고, 해당 카드의 수익성 유지가 어려워져 부가서비스를 변경하는 경우에는 6개월 전부터 매월 개별고지 해 드립니다.",
    "• 개별고지 방법 : 카드대금청구서, 우편, 이메일, 휴대전화 문자메세지 중 하나"
  ]
}