{
  "card_id": 2797,
  "card_url": "https://www.card-gorilla.com/card/detail/2797",
  "card_name": "SKT T다운 하나카드",
  "issuer": "하나카드",
  "inactive": "신규발급이 중단된 카드입니다.",
  "brands": [
    "VISA",
    "Mastercard"
  ],
  "annual_fee": {
    "domestic": "국내전용 25,000원",
    "international": "해외겸용 25,000원"
  },
  "required_spending": null,
  "required_spending_amount": null,
  "benefits": [
    {
      "type": "SKT",
      "summary": "SKT 라이트할부 청구할인",
      "details": [
        "1. SKT 라이트할부 청구할인(T라이트 할부 서비스 이용 시)",
        "2. 기본할인(T라이트 할부 미이용시)",
        "서비스 제공 조건",
        "실적 산정 기준",
        "지난달 1일부터 말일(승인 시점 기준)까지 국내외 일시불/할부 이용금액 40만원 이상/80만원 이상 시 서비스 차등 제공",
        "실적 제외 대상",
        "국세, 지방세, 공과금(인터넷/모바일 앱을 통한 공과금 납부 금액 포함), 수도/전기요금, 도시가스 요금, 아파트관리비, 국민연금/고용보험료/산재보험료/건강보험료 납부 금액, 스쿨뱅킹, 초.중.고 학교 납입금, 대학등록금, 대학원등록금, 상품권(모바일 온누리 상품권 구매 포함) 및 기프트카드 구매, 선불카드 및 선불전자지급수단(하나머니 등) 충전 금액, 부동산임대료, 무이자할부 매출",
        "실적과 관계없이 서비스 제공",
        "최초 카드 사용등록일로부터 다음 달 말일까지는 지난달 카드 실적 40만원 미만이어도 40만원 이상 80만원 미만 기준 서비스 제공"
      ]
    }
  ],
  "caution": []
}