{
  "card_id": 1383,
  "card_url": "https://www.card-gorilla.com/card/detail/1383",
  "card_name": "반려愛카드(강아지)",
  "issuer": "KB국민카드",
  "inactive": false,
  "brands": [
    "Mastercard",
    "JCB"
  ],
  "annual_fee": {
    "domestic": "해외겸용 8,000원",
    "international": null
  },
  "required_spending": null,
  "required_spending_amount": null,
  "benefits": [
    {
      "type": "애완동물",
      "summary": "반려동물 업종 10% 할인 반려동물 보호를 위한 공익기금 조성",
      "details": [
        "반려동물 업종 10% 할인",
        "반려동물 업종 이용 시 10% 청구할인\n* 반려동물 업종 : 동물병원, 애완동물 업종 (펫샵, 동물검사소, 관련 약품 구매, 장례업체 포함)",
        "[1구간] 전월 이용실적 30만원 이상: 월 할인한도 2만원",
        "[2구간] 전월 이용실적 60만원 이상: 월 할인한도 3만원",
        "[3구간] 전월 이용실적 90만원 이상: 월 할인한도 5만원",
        "최초 카드 사용등록일로부터 다음달 말일까지 KB국민 반려愛카드 이용실적이 없는 경우에도 1구간 서비스 제공",
        "백화점/대형마트 입점, PG(인터넷결제) 가맹점 이용금액 제외",
        "반려동물 보호를 위한 공익기금 조성",
        "별도 비용 부담 없이 KB국민 반려愛카드 이용금액의 일정비율을 유기 반려동물 등 동물보호를 위한 공익사업에 활용"
      ]
    },
    {
      "type": "대형마트",
      "summary": "이마트 · 롯데마트 · 홈플러스 5%청구할인",
      "details": [
        "이마트 · 롯데마트 · 홈플러스 5%청구할인",
        "[1구간] 전월 이용실적 30만원 이상: 월 할인한도 5천원",
        "[2구간] 전월 이용실적 60만원 이상: 월 할인한도 1만원",
        "최초 카드 사용등록일로부터 다음달 말일까지 KB국민 반려愛카드 이용실적이 없는 경우에도 1구간 서비스 제공",
        "백화점/대형마트 입점, PG(인터넷결제) 가맹점 이용금액 제외"
      ]
    },
    {
      "type": "온라인쇼핑",
      "summary": "G마켓 · 옥션 · 인터파크 · 11번가 5%청구할인",
      "details": [
        "G마켓 · 옥션 · 인터파크 · 11번가 5%청구할인",
        "[1구간] 전월 이용실적 30만원 이상: 월 할인한도 5천원",
        "[2구간] 전월 이용실적 60만원 이상: 월 할인한도 1만원",
        "최초 카드 사용등록일로부터 다음달 말일까지 KB국민 반려愛카드 이용실적이 없는 경우에도 1구간 서비스 제공",
        "온라인쇼핑몰/슈퍼(익스프레스) 이용금액, 상품권 구매 및 건물 내 임대매장 이용금액 제외"
      ]
    }
  ],
  "caution": []
}